weconnect_cli/__init__.py
weconnect_cli/__main__.py
weconnect_cli/__version.py
weconnect_cli/weconnect_cli_base.py
weconnect_cli-0.38.7.dist-info/LICENSE
weconnect_cli-0.38.7.dist-info/METADATA
weconnect_cli-0.38.7.dist-info/WHEEL
weconnect_cli-0.38.7.dist-info/entry_points.txt
weconnect_cli-0.38.7.dist-info/top_level.txt
weconnect_cli-0.38.7.dist-info/RECORD
