Metadata-Version: 2.1
Name: weconnect-cli
Version: 0.38.7
Summary: Commandline Interface to interact with the Volkswagen WeConnect Services
Home-page: https://github.com/tillsteinbach/WeConnect-cli
Author: Till Steinbach
License: MIT
Project-URL: Funding, https://github.com/sponsors/tillsteinbach
Project-URL: Source, https://github.com/tillsteinbach/WeConnect-cli
Project-URL: Bug Tracker, https://github.com/tillsteinbach/WeConnect-cli/issues
Keywords: weconnect,we connect,carnet,car net,volkswagen,vw,telemetry
Classifier: Development Status :: 3 - Alpha
Classifier: Environment :: Console
Classifier: License :: OSI Approved :: MIT License
Classifier: Intended Audience :: End Users/Desktop
Classifier: Intended Audience :: System Administrators
Classifier: Programming Language :: Python :: 3.8
Classifier: Programming Language :: Python :: 3.9
Classifier: Programming Language :: Python :: 3.10
Classifier: Programming Language :: Python :: 3.11
Classifier: Programming Language :: Python :: 3.12
Classifier: Topic :: Utilities
Classifier: Topic :: System :: Monitoring
Requires-Python: >=3.8
License-File: LICENSE
Requires-Dist: weconnect[images]~=0.60.5
